siglab_py/__init__.py
siglab_py/constants.py
siglab_py/exchanges/__init__.py
siglab_py/exchanges/any_exchange.py
siglab_py/market_data_providers/__init__.py
siglab_py/market_data_providers/aggregated_orderbook_provider.py
siglab_py/market_data_providers/candles_provider.py
siglab_py/market_data_providers/candles_ta_provider.py
siglab_py/market_data_providers/deribit_options_expiry_provider.py
siglab_py/market_data_providers/orderbooks_provider.py
siglab_py/market_data_providers/test_provider.py
siglab_py/ordergateway/__init__.py
siglab_py/ordergateway/client.py
siglab_py/ordergateway/encrypt_keys_util.py
siglab_py/ordergateway/gateway.py
siglab_py/ordergateway/test_ordergateway.py
siglab_py/tests/__init__.py
siglab_py/tests/integration/__init__.py
siglab_py/tests/integration/market_data_util_tests.py
siglab_py/tests/unit/__init__.py
siglab_py/util/__init__.py
siglab_py/util/analytic_util.py
siglab_py/util/aws_util.py
siglab_py/util/market_data_util.py
siglab_py/util/retry_util.py
siglib_py-0.1.6.dist-info/METADATA
siglib_py-0.1.6.dist-info/WHEEL
siglib_py-0.1.6.dist-info/top_level.txt
siglib_py-0.1.6.dist-info/RECORD
