Metadata-Version: 2.1
Name: siglib-py
Version: 0.1.6
Summary: Market data fetches, TA calculations and generic order gateway.
Author: r0bbarh00d
Author-email: r0bbarh00d <r0bbarh00d@gmail.com>
License: MIT
Project-URL: Homepage, https://github.com/r0bbar/siglab/blob/master/siglab_py/README.md
Classifier: Programming Language :: Python :: 3
Classifier: License :: OSI Approved :: MIT License
Classifier: Operating System :: OS Independent
Requires-Python: >=3.9.19
Requires-Dist: python-dotenv
Requires-Dist: dotmap
Requires-Dist: typing-extensions
Requires-Dist: arrow
Requires-Dist: tzlocal
Requires-Dist: nest-asyncio
Requires-Dist: pandas
Requires-Dist: numpy
Requires-Dist: boto3
Requires-Dist: web3
Requires-Dist: ccxt
Requires-Dist: ccxtpro
Requires-Dist: yfinance
Requires-Dist: yahoofinancials
Requires-Dist: scipy
Requires-Dist: statsmodels
Requires-Dist: scikit-learn
Requires-Dist: sklearn.preprocessing
Requires-Dist: hurst
Requires-Dist: redis
Requires-Dist: redis-py-cluster
Requires-Dist: kafka-python
